asyncipfscluster/__init__.py
asyncipfscluster/client.py
asyncipfscluster/exceptions.py
asyncipfscluster-0.1.2.dist-info/LICENSE
asyncipfscluster-0.1.2.dist-info/WHEEL
asyncipfscluster-0.1.2.dist-info/METADATA
asyncipfscluster-0.1.2.dist-info/RECORD
